{
	"name": "rlm_linelog",
	"description": "rlm_linelog description",
	"category": "io",
	"documentation_link": "http://networkradius.com/doc/current/raddb/mods-available/linelog",
	"available": [
		{
			"branch": {
				"name": "test_branch_a",
				"url": "/api/info/branch/test_branch_a/"
			},
			"start": {
				"name": "0.0.1",
				"url": "/api/info/branch/test_branch_a/release/0.0.1/"
			},
			"end": {
				"name": "0.0.2",
				"url": "/api/info/branch/test_branch_a/release/0.0.2/"
			}
		}
	]
}
